HISTORY.rst
LICENSE
MANIFEST.in
README.rst
setup.py
django_commontranslations/__init__.py
django_commontranslations/models.py
django_commontranslations.egg-info/PKG-INFO
django_commontranslations.egg-info/SOURCES.txt
django_commontranslations.egg-info/dependency_links.txt
django_commontranslations.egg-info/not-zip-safe
django_commontranslations.egg-info/requires.txt
django_commontranslations.egg-info/top_level.txt
django_commontranslations/locale/de/LC_MESSAGES/django.po
django_commontranslations/locale/en/LC_MESSAGES/django.po
django_commontranslations/locale/fr/LC_MESSAGES/django.po
django_commontranslations/management/__init__.py
django_commontranslations/management/commands/__init__.py
django_commontranslations/management/commands/makemessages_unique.py
django_commontranslations/translations/__init__.py
django_commontranslations/translations/languages.py
django_commontranslations/translations/navigation.py