Metadata-Version: 1.1
Name: django-commontranslations
Version: 0.1a2
Summary: prevents repeating translations across apps and projects
Home-page: http://github.com/divio/django-commontranslations
Author: Stefan Foulis (Divio AG)
Author-email: stefan@foulis.ch
License: BSD
Platform: OS Independent
Classifier: Development Status :: 3 - Alpha
Classifier: Framework :: Django
Classifier: Intended Audience :: Developers
Classifier: License :: OSI Approved :: BSD License
Classifier: Operating System :: OS Independent
Classifier: Programming Language :: Python
Classifier: Topic :: Internet :: WWW/HTTP
